setup.py
atk_satish_helloworld/__init__.py
atk_satish_helloworld/hello.py
atk_satish_helloworld/setup.py
atk_satish_helloworld.egg-info/PKG-INFO
atk_satish_helloworld.egg-info/SOURCES.txt
atk_satish_helloworld.egg-info/dependency_links.txt
atk_satish_helloworld.egg-info/top_level.txt