Metadata-Version: 2.1
Name: atk-satish-helloworld
Version: 0.3
Summary: A 'Hello, World!' package
Author: Satish Kumar
Author-email: satish@aganitha.com
